midiexplorer/__about__.py
midiexplorer/__config__.py
midiexplorer/__init__.py
midiexplorer/__main__.py
midiexplorer/fonts/Roboto-Regular.ttf
midiexplorer/fonts/RobotoMono-Regular.ttf
midiexplorer/fonts/__init__.py
midiexplorer/gui/__init__.py
midiexplorer/gui/helpers/__init__.py
midiexplorer/gui/helpers/config.py
midiexplorer/gui/helpers/convert.py
midiexplorer/gui/helpers/logger.py
midiexplorer/gui/helpers/menu.py
midiexplorer/gui/helpers/probe.py
midiexplorer/gui/helpers/smf.py
midiexplorer/gui/helpers/callbacks/__init__.py
midiexplorer/gui/helpers/callbacks/_sample.py
midiexplorer/gui/helpers/callbacks/debugging.py
midiexplorer/gui/helpers/constants/__init__.py
midiexplorer/gui/helpers/constants/slots.py
midiexplorer/gui/windows/__init__.py
midiexplorer/gui/windows/about.py
midiexplorer/gui/windows/conn.py
midiexplorer/gui/windows/gen.py
midiexplorer/gui/windows/log.py
midiexplorer/gui/windows/smf.py
midiexplorer/gui/windows/hist/__init__.py
midiexplorer/gui/windows/hist/data.py
midiexplorer/gui/windows/mon/__init__.py
midiexplorer/gui/windows/mon/blink.py
midiexplorer/gui/windows/mon/data.py
midiexplorer/gui/windows/mon/settings.py
midiexplorer/icons/__init__.py
midiexplorer/icons/gplv3-or-later-sm.png
midiexplorer/icons/gplv3-or-later.png
midiexplorer/icons/midiexplorer.ico
midiexplorer/icons/midiexplorer.svg
midiexplorer/icons/midiexplorer_128.png
midiexplorer/icons/midiexplorer_16.png
midiexplorer/icons/midiexplorer_256.png
midiexplorer/icons/midiexplorer_32.png
midiexplorer/icons/midiexplorer_48.png
midiexplorer/icons/midiexplorer_512.png
midiexplorer/icons/midiexplorer_64.png
midiexplorer/icons/midiexplorer_96.png
midiexplorer/midi/MIDI Implementation Chart v1.0 Sample.rst
midiexplorer/midi/MIDI Implementation Chart v2.0 Sample.rst
midiexplorer/midi/__init__.py
midiexplorer/midi/mido2standard.py
midiexplorer/midi/notes.py
midiexplorer/midi/ports.py
midiexplorer/midi/timestamp.py
midiexplorer/midi/decoders/__init__.py
midiexplorer/midi/decoders/sysex.py
midiexplorer-0.0.1a5.dist-info/METADATA
midiexplorer-0.0.1a5.dist-info/WHEEL
midiexplorer-0.0.1a5.dist-info/entry_points.txt
midiexplorer-0.0.1a5.dist-info/licenses/LICENSE
midiexplorer-0.0.1a5.dist-info/RECORD
