Metadata-Version: 2.1
Name: midiexplorer
Version: 0.0.1a5
Summary: Yet another MIDI monitor, analyzer, debugger and manipulation tool.
Project-URL: Homepage, https://github.com/ematech/midiexplorer
Project-URL: Issues, https://github.com/ematech/midiexplorer/issues
Author-email: Raphaël Doursenaud <rdoursenaud@free.fr>
License:                     GNU GENERAL PUBLIC LICENSE
License-File: LICENSE
Keywords: Analyzer,Debugger,MIDI
Classifier: Development Status :: 3 - Alpha
Classifier: Environment :: MacOS X
Classifier: Environment :: Win32 (MS Windows)
Classifier: Environment :: X11 Applications
Classifier: Intended Audience :: Customer Service
Classifier: Intended Audience :: Developers
Classifier: Intended Audience :: Education
Classifier: Intended Audience :: End Users/Desktop
Classifier: Intended Audience :: Information Technology
Classifier: Intended Audience :: Manufacturing
Classifier: Intended Audience :: Other Audience
Classifier: Intended Audience :: Science/Research
Classifier: Intended Audience :: System Administrators
Classifier: Intended Audience :: Telecommunications Industry
Classifier: License :: OSI Approved :: GNU General Public License v3 or later (GPLv3+)
Classifier: Natural Language :: English
Classifier: Operating System :: MacOS :: MacOS X
Classifier: Operating System :: Microsoft :: Windows :: Windows 10
Classifier: Operating System :: Microsoft :: Windows :: Windows 11
Classifier: Operating System :: POSIX :: Linux
Classifier: Programming Language :: Python :: 3
Classifier: Programming Language :: Python :: 3 :: Only
Classifier: Programming Language :: Python :: 3.10
Classifier: Topic :: Artistic Software
Classifier: Topic :: Communications
Classifier: Topic :: Education :: Testing
Classifier: Topic :: Home Automation
Classifier: Topic :: Multimedia :: Sound/Audio :: Analysis
Classifier: Topic :: Multimedia :: Sound/Audio :: MIDI
Classifier: Topic :: Scientific/Engineering
Classifier: Topic :: Scientific/Engineering :: Human Machine Interfaces
Classifier: Topic :: Scientific/Engineering :: Information Analysis
Classifier: Topic :: Scientific/Engineering :: Interface Engine/Protocol Translator
Classifier: Topic :: Scientific/Engineering :: Visualization
Classifier: Topic :: Software Development :: Debuggers
Classifier: Topic :: Software Development :: Embedded Systems
Classifier: Topic :: Software Development :: Quality Assurance
Classifier: Topic :: Software Development :: Testing
Classifier: Topic :: System :: Hardware :: Universal Serial Bus (USB) :: Audio
Classifier: Topic :: System :: Monitoring
Classifier: Topic :: Utilities
Classifier: Typing :: Typed
Requires-Python: >=3.10
Requires-Dist: dearpygui-ext~=0.9.5
Requires-Dist: dearpygui~=1.8.0
Requires-Dist: midi-const~=0.1.0
Requires-Dist: mido~=1.3.0
Requires-Dist: pillow~=9.5.0
Requires-Dist: python-rtmidi~=1.5.5
